{
  "meta": {
    "id": "phase2_queries_graph_osm_pune_india"
  },
  "events": [
    {
      "id": 1,
      "type": "approx_shortest_path",
      "queries": [
        {
          "source": 4,
          "target": 3
        },
        {
          "source": 0,
          "target": 9
        },
        {
          "source": 0,
          "target": 2
        },
        {
          "source": 4,
          "target": 0
        },
        {
          "source": 1,
          "target": 3
        },
        {
          "source": 3,
          "target": 7
        },
        {
          "source": 7,
          "target": 2
        },
        {
          "source": 3,
          "target": 9
        },
        {
          "source": 8,
          "target": 6
        },
        {
          "source": 1,
          "target": 2
        },
        {
          "source": 9,
          "target": 7
        },
        {
          "source": 9,
          "target": 1
        },
        {
          "source": 5,
          "target": 6
        },
        {
          "source": 4,
          "target": 3
        }
      ],
      "time_budget_ms": 27,
      "acceptable_error_pct": 10.0
    },
    {
      "id": 3,
      "type": "k_shortest_paths_heuristic",
      "source": 9,
      "target": 2,
      "k": 5,
      "overlap_threshold": 64
    },
    {
      "id": 5,
      "type": "k_shortest_paths_heuristic",
      "source": 3,
      "target": 0,
      "k": 2,
      "overlap_threshold": 65
    },
    {
      "id": 7,
      "type": "k_shortest_paths",
      "source": 7,
      "target": 1,
      "k": 3,
      "mode": "distance"
    },
    {
      "id": 8,
      "type": "k_shortest_paths",
      "source": 1,
      "target": 6,
      "k": 16,
      "mode": "distance"
    },
    {
      "id": 11,
      "type": "k_shortest_paths",
      "source": 5,
      "target": 7,
      "k": 15,
      "mode": "distance"
    }
  ]
}